featdist/__init__.py
featdist/base.py
featdist-0.1.6.dist-info/LICENSE
featdist-0.1.6.dist-info/METADATA
featdist-0.1.6.dist-info/WHEEL
featdist-0.1.6.dist-info/top_level.txt
featdist-0.1.6.dist-info/RECORD
