Metadata-Version: 2.1
Name: featdist
Version: 0.1.6
Summary: Train test target distribution function for machine learning
Home-page: https://github.com/Hasan-Basri-Akcay/featdist
Author: Hasan Basri Akcay
Author-email: hasan.basri.akcay@gmail.com
Keywords: python,data science,data analysis,exploratory data analysis,distribution,beginner
Classifier: Programming Language :: Python :: 3
Classifier: Programming Language :: Python :: 2
Classifier: License :: OSI Approved :: MIT License
Classifier: Operating System :: OS Independent
License-File: LICENSE
Requires-Dist: pandas
Requires-Dist: numpy
Requires-Dist: matplotlib
